Pysolbook.py
README.md
setup.py
Pysolbook.egg-info/PKG-INFO
Pysolbook.egg-info/SOURCES.txt
Pysolbook.egg-info/dependency_links.txt
Pysolbook.egg-info/top_level.txt