Metadata-Version: 2.1
Name: Pysolbook
Version: 1.0.1
Summary: Automatically find solutions to Python exercise questions by providing the question number or text as input.
Home-page: https://github.com/arman229/python-coding-journey.git
Author: Arman
Author-email: armanashraf015@gmail.com
License: MIT
